OwaisAamir_STT/__init__.py
OwaisAamir_STT-1.1.dist-info/METADATA
OwaisAamir_STT-1.1.dist-info/WHEEL
OwaisAamir_STT-1.1.dist-info/top_level.txt
OwaisAamir_STT-1.1.dist-info/RECORD
