Metadata-Version: 2.1
Name: OwaisAamir-STT
Version: 1.1
Summary: this is speech to text package create by Muhammad Owais Aamir
Author: Muhammad Owais Aamir
Author-email: owaisaamir53@gmail.com
